{
  "meta": {
    "id": "71f2bae9-fee8-4eb4-8d3e-f249e5196a31",
    "schema_version": "v1",
    "title": "2020年AI算法岗求职群",
    "slug": "2020年ai算法岗求职群",
    "path": "docs/学习文档/deep-learning-interview-book/docs/imgs/2020年ai算法岗求职群.json",
    "parent_id": "9655dc10-1085-427b-a570-eca3249e8d45",
    "created_at": "2026-01-31T02:03:13.846Z",
    "updated_at": "2026-01-31T02:03:13.846Z",
    "extra": {
      "status": "draft",
      "tags": []
    }
  },
  "body": {
    "type": "tiptap",
    "content": {
      "type": "doc",
      "content": [
        {
          "type": "file_block",
          "attrs": {
            "asset_id": "43c0cd70-fb74-47b7-a22d-e06fd11565fe",
            "file_name": "2020年AI算法岗求职群.png",
            "mime": "image/png",
            "size": 62862,
            "file_type": "unknown"
          }
        }
      ]
    }
  }
}